sapphiredl/__init__.py
sapphiredl/data/__init__.py
sapphiredl/data/data.py
sapphiredl/examples/__init__.py
sapphiredl/examples/fizzbuzz.py
sapphiredl/examples/xor.py
sapphiredl/layers/__init__.py
sapphiredl/layers/activation/__init__.py
sapphiredl/layers/activation/activation_layers.py
sapphiredl/layers/activation/base_activation.py
sapphiredl/layers/activation/func_tools.py
sapphiredl/layers/meaning/__init__.py
sapphiredl/layers/meaning/base.py
sapphiredl/layers/meaning/layers_of_meaning.py
sapphiredl/loss_functions/__init__.py
sapphiredl/loss_functions/base.py
sapphiredl/loss_functions/regression_loss.py
sapphiredl/loss_functions/relative_loss.py
sapphiredl/neural_networks/__init__.py
sapphiredl/neural_networks/neu_net.py
sapphiredl/optimizers/__init__.py
sapphiredl/optimizers/base.py
sapphiredl/optimizers/optim.py
sapphiredl/tensors/__init__.py
sapphiredl/tensors/tensor_type.py
sapphiredl/training/__init__.py
sapphiredl/training/train.py
SapphireDL-0.1.6.dist-info/METADATA
SapphireDL-0.1.6.dist-info/WHEEL
SapphireDL-0.1.6.dist-info/top_level.txt
SapphireDL-0.1.6.dist-info/RECORD
