Metadata-Version: 2.1
Name: SapphireDL
Version: 0.1.6
Summary: Library for simple DL structure
Home-page: https://github.com/itbert/Sapphire-DL
Author: Albert
Requires-Dist: numpy~=2.1.2
Requires-Dist: setuptools~=75.3.0
